telenal/.env
telenal/__init__.py
telenal/account.py
telenal/analysis.py
telenal/client.py
telenal/image.png
telenal/my_account.session
telenal/my_account.session-journal
telenal/reactions.py
telenal/teleplotter.py
telegram_anal-0.1.1.dist-info/WHEEL
telegram_anal-0.1.1.dist-info/METADATA
telegram_anal-0.1.1.dist-info/RECORD
