Metadata-Version: 2.1
Name: telegram-anal
Version: 0.1.1
Summary: A fun tool to play with Telegram chats
Home-page: https://github.com/Salz0/Telegram-anal
License: GPL-3.0-or-later
Keywords: telegram,analysis,nlp
Author: Vladyslav Bilyk
Author-email: vladozeransky2k@gmail.com
Requires-Python: >=3.10,<4.0
Classifier: License :: OSI Approved :: GNU General Public License v3 or later (GPLv3+)
Classifier: Programming Language :: Python :: 3
Classifier: Programming Language :: Python :: 3.10
Requires-Dist: Pyrogram (>=2.0.59,<3.0.0)
Requires-Dist: TgCrypto (>=1.2.4,<2.0.0)
Requires-Dist: matplotlib (>=3.6.1,<4.0.0)
Requires-Dist: nltk (>=3.7,<4.0)
Requires-Dist: numpy (>=1.23.4,<2.0.0)
Requires-Dist: pandas (>=1.5.1,<2.0.0)
Requires-Dist: python-dotenv (>=0.21.0,<0.22.0)
Requires-Dist: scipy (>=1.9.3,<2.0.0)
Requires-Dist: stop-words (>=2018.7.23,<2019.0.0)
Requires-Dist: wordcloud (>=1.8.2,<2.0.0)
Project-URL: Repository, https://github.com/Salz0/Telegram-anal
